configurable/__init__.py
configurable/configurable.py
configurable/schema.py
configurable/utils.py
configurable_cl-0.1.7.dist-info/LICENSE
configurable_cl-0.1.7.dist-info/METADATA
configurable_cl-0.1.7.dist-info/WHEEL
configurable_cl-0.1.7.dist-info/top_level.txt
configurable_cl-0.1.7.dist-info/RECORD
