Metadata-Version: 2.1
Name: configurable-cl
Version: 0.1.7
Summary: This module provides classes and utilities for managing configurations, validating schemas, and creating Configurable objects from configuration data. It is particularly useful for AI applications where configurations can be complex and need to be validated at runtime.
Home-page: https://github.com/JulienRabault/Configurable-cl
Author: Julien Rabault
Author-email: Julien Rabault <julienrabault@icloud.com>
License: MIT
Project-URL: Homepage, https://github.com/JulienRabault/Configurable-cl
Classifier: Programming Language :: Python :: 3
Classifier: License :: OSI Approved :: MIT License
Classifier: Operating System :: OS Independent
Requires-Python: >=3.8
License-File: LICENSE
Requires-Dist: wheel
Requires-Dist: PyYAML
Requires-Dist: pytest
Requires-Dist: typing-extensions
